refind_btrfs/__init__.py
refind_btrfs/__main__.py
refind_btrfs/boot/__init__.py
refind_btrfs/boot/boot_options.py
refind_btrfs/boot/boot_stanza.py
refind_btrfs/boot/file_refind_config_provider.py
refind_btrfs/boot/refind_config.py
refind_btrfs/boot/refind_listeners.py
refind_btrfs/boot/refind_visitors.py
refind_btrfs/boot/sub_menu.py
refind_btrfs/boot/antlr4/RefindConfigLexer.py
refind_btrfs/boot/antlr4/RefindConfigParser.py
refind_btrfs/boot/antlr4/RefindConfigParserVisitor.py
refind_btrfs/boot/antlr4/__init__.py
refind_btrfs/boot/migrations/__init__.py
refind_btrfs/boot/migrations/icon_migration_strategies.py
refind_btrfs/boot/migrations/main_migration_strategies.py
refind_btrfs/boot/migrations/migration.py
refind_btrfs/boot/migrations/state.py
refind_btrfs/common/__init__.py
refind_btrfs/common/boot_files_check_result.py
refind_btrfs/common/checkable_observer.py
refind_btrfs/common/configurable_mixin.py
refind_btrfs/common/constants.py
refind_btrfs/common/enums.py
refind_btrfs/common/exceptions.py
refind_btrfs/common/package_config.py
refind_btrfs/common/abc/__init__.py
refind_btrfs/common/abc/base_config.py
refind_btrfs/common/abc/base_runner.py
refind_btrfs/common/abc/commands/__init__.py
refind_btrfs/common/abc/commands/device_command.py
refind_btrfs/common/abc/commands/icon_command.py
refind_btrfs/common/abc/commands/subvolume_command.py
refind_btrfs/common/abc/factories/__init__.py
refind_btrfs/common/abc/factories/base_device_command_factory.py
refind_btrfs/common/abc/factories/base_icon_command_factory.py
refind_btrfs/common/abc/factories/base_logger_factory.py
refind_btrfs/common/abc/factories/base_subvolume_command_factory.py
refind_btrfs/common/abc/providers/__init__.py
refind_btrfs/common/abc/providers/base_package_config_provider.py
refind_btrfs/common/abc/providers/base_persistence_provider.py
refind_btrfs/common/abc/providers/base_refind_config_provider.py
refind_btrfs/console/__init__.py
refind_btrfs/console/cli_runner.py
refind_btrfs-0.6.5.dist-info/licenses/LICENSE.txt
refind_btrfs-0.6.5.dist-info/METADATA
refind_btrfs-0.6.5.dist-info/WHEEL
refind_btrfs-0.6.5.dist-info/entry_points.txt
refind_btrfs-0.6.5.dist-info/top_level.txt
refind_btrfs-0.6.5.dist-info/RECORD
