Metadata-Version: 2.4
Name: refind-btrfs
Version: 0.6.5
Summary: Generate rEFInd manual boot stanzas from Btrfs snapshots
Home-page: https://github.com/Venom1991/refind-btrfs
Author: Luka Žaja
Author-email: luka.zaja@protonmail.com
Maintainer: Luka Žaja
Maintainer-email: luka.zaja@protonmail.com
License: GNU General Public License v3 or later (GPLv3+)
Keywords: rEFInd,btrfs
Platform: Linux
Classifier: Development Status :: 4 - Beta
Classifier: Intended Audience :: End Users/Desktop
Classifier: License :: OSI Approved :: GNU General Public License v3 or later (GPLv3+)
Classifier: Natural Language :: English
Classifier: Operating System :: POSIX :: Linux
Classifier: Programming Language :: Python :: 3.11
Classifier: Topic :: System :: Boot
Requires-Python: >=3.11
License-File: LICENSE.txt
Requires-Dist: antlr4-python3-runtime
Requires-Dist: injector
Requires-Dist: more-itertools
Requires-Dist: pid
Requires-Dist: semantic-version
Requires-Dist: systemd-python
Requires-Dist: tomlkit
Requires-Dist: transitions
Requires-Dist: typeguard
Requires-Dist: watchdog
Provides-Extra: custom-icon
Requires-Dist: Pillow; extra == "custom-icon"
Dynamic: author
Dynamic: author-email
Dynamic: classifier
Dynamic: description
Dynamic: description-content-type
Dynamic: home-page
Dynamic: keywords
Dynamic: license-file
Dynamic: provides-extra
Dynamic: requires-dist
Dynamic: requires-python
Dynamic: summary
